{
  "url": "https://www.microvista.de/en/research-development/",
  "slug": "en/research-development",
  "title": "Promotion of research & development",
  "type": "page",
  "lang": "en",
  "metaDescription": "Find out about the topics in which Microvista GmbH is active & engaged in research & development.",
  "ogImage": "https://www.microvista.de/wp-content/uploads/2022/06/ESF_rgb_print.jpg",
  "canonical": "https://www.microvista.de/en/research-development/",
  "markdown": "# RESEARCH AND DEVELOPMENT  \nAT MICROVISTA\n\nGET YOUR INSPECTION DONE – Anywhere. Anytime. Fast.\n\n[Express-Inspection  \nbooking](https://www.microvista.de/en/contact/)\n\n[Schedule free consultation  \nhere!](https://www.microvista.de/en/contact/)",
  "htmlLength": 4322,
  "markdownLength": 243,
  "images": [
    "https://www.microvista.de/wp-content/uploads/2022/06/ESF_rgb_print-768x129.jpg",
    "https://www.microvista.de/wp-content/uploads/2022/06/ESF_rgb_print-300x51.jpg",
    "https://www.microvista.de/wp-content/uploads/2022/06/ESF_rgb_print-1024x173.jpg",
    "https://www.microvista.de/wp-content/uploads/2022/06/ESF_rgb_print.jpg",
    "https://www.microvista.de/wp-content/uploads/2022/06/ESF_hier.investiert.europa.in_.d.zukunft_4c_print-002-768x160.jpg",
    "https://www.microvista.de/wp-content/uploads/2022/06/ESF_hier.investiert.europa.in_.d.zukunft_4c_print-002-300x63.jpg",
    "https://www.microvista.de/wp-content/uploads/2022/06/ESF_hier.investiert.europa.in_.d.zukunft_4c_print-002-1024x214.jpg",
    "https://www.microvista.de/wp-content/uploads/2022/06/ESF_hier.investiert.europa.in_.d.zukunft_4c_print-002-1536x321.jpg",
    "https://www.microvista.de/wp-content/uploads/2022/06/ESF_hier.investiert.europa.in_.d.zukunft_4c_print-002.jpg"
  ],
  "scrapedAt": "2026-02-26T09:48:34.929Z"
}